<?xml version="1.0" encoding="UTF-8" standalone="yes"?>
<nifty xmlns:xsi="http://www.w3.org/2001/XMLSchema-instance" xmlns="http://nifty-gui.lessvoid.com/nifty-gui" xsi:schemaLocation="https://raw.githubusercontent.com/void256/nifty-gui/1.4/nifty-core/src/main/resources/nifty.xsd https://raw.githubusercontent.com/void256/nifty-gui/1.4/nifty-core/src/main/resources/nifty.xsd">
    <useControls filename="nifty-default-controls.xml"/>
    <useStyles filename="nifty-default-styles.xml"/>
    <screen id="start" controller="mygame.Main">
        <layer id="startLayer" childLayout="absolute">
            <control name="button" label="Start" id="StartButton" x="122" y="300"  align="center" valign="center" 
                     visibleToMouse="true" > 
                <interact onClick="switchGameState()"/>
            </control>
            <control name="button" label="Options" id="OptionsButton" x="122" y="330"  align="center" valign="center" 
                     visibleToMouse="true" > 
                <interact onClick="switchOptionsState()"/>
            </control>
        </layer>
    </screen>
</nifty>